zendesk_sell_firehose_client/__init__.py
zendesk_sell_firehose_client-0.0.5.dist-info/LICENSE
zendesk_sell_firehose_client-0.0.5.dist-info/METADATA
zendesk_sell_firehose_client-0.0.5.dist-info/WHEEL
zendesk_sell_firehose_client-0.0.5.dist-info/top_level.txt
zendesk_sell_firehose_client-0.0.5.dist-info/RECORD
