Metadata-Version: 2.1
Name: zendesk-sell-firehose-client
Version: 0.0.5
Summary: Client for ZenDesk Sell Firehose API
Author-email: StrongMind <teambelding@strongmind.com>, Mark Ng <mark.ng@strongmind.com>, Paul Shippy <paul.shippy@strongmind.com>
Project-URL: Homepage, https://github.com/StrongMind/zendesk_sell_firehose_client
Project-URL: Bug Tracker, https://github.com/StrongMind/zendesk_sell_firehose_client/issues
Classifier: Programming Language :: Python :: 3
Classifier: License :: OSI Approved :: MIT License
Classifier: Operating System :: OS Independent
Requires-Python: >=3.7
License-File: LICENSE
Requires-Dist: requests (>=2.22.0)
Provides-Extra: dev
Requires-Dist: pytest ; extra == 'dev'
Requires-Dist: pytest-describe ; extra == 'dev'
